<?xml version="1.0" encoding="UTF-8" standalone="no"?><Accounts><User id="710984"><UserName>Aurelien</UserName><Password>231199</Password><Contacts><Contact>Roman</Contact></Contacts><Groups><Group><Member>Aurelien</Member></Group></Groups></User><User id="899988"><UserName>Roman</UserName><Password>250599</Password><Contacts><Contact>Aurelien</Contact></Contacts><Groups/></User><User id="91995"><UserName>Nils</UserName><Password>Chol</Password><Contacts><Contact>Roman</Contact><Contact>Aurelien</Contact></Contacts><Groups><Group><Member>Roman</Member><Member>Aurelien</Member><Member>Nils</Member></Group></Groups></User></Accounts>